enochian_studio/__init__.py
enochian_studio/cli.py
enochian_studio/installer.py
enochian_studio/node_runner.py
enochian_studio/package.json
enochian_studio-0.0.5.dist-info/METADATA
enochian_studio-0.0.5.dist-info/WHEEL
enochian_studio-0.0.5.dist-info/entry_points.txt
enochian_studio-0.0.5.dist-info/licenses/LICENSE
enochian_studio-0.0.5.dist-info/RECORD
