Metadata-Version: 2.3
Name: enochian_studio
Version: 0.0.5
Summary: Python wrapper for enochian-studio npm package
Project-URL: Homepage, https://zolinthecow.mintlify.app
Project-URL: Repository, https://github.com/zolinthecow/enochian-js/tree/master/studio-python
Author-email: Colin Zhao <colinzhao777@gmail.com>
License: MIT License
Classifier: Development Status :: 3 - Alpha
Classifier: Intended Audience :: Developers
Classifier: License :: OSI Approved :: MIT License
Classifier: Programming Language :: Python :: 3
Classifier: Programming Language :: Python :: 3.8
Classifier: Programming Language :: Python :: 3.9
Classifier: Programming Language :: Python :: 3.10
Classifier: Programming Language :: Python :: 3.11
Requires-Python: >=3.8
